streamlit_gsheets/__init__.py
streamlit_gsheets/gsheets_connection.py
gsheets_connector-1.4.0.dist-info/METADATA
gsheets_connector-1.4.0.dist-info/WHEEL
gsheets_connector-1.4.0.dist-info/top_level.txt
gsheets_connector-1.4.0.dist-info/RECORD
